pyscada/__init__.py
pyscada/opcua/__init__.py
pyscada/opcua/admin.py
pyscada/opcua/apps.py
pyscada/opcua/device.py
pyscada/opcua/models.py
pyscada/opcua/signals.py
pyscada/opcua/worker.py
pyscada/opcua/devices/__init__.py
pyscada/opcua/migrations/0001_initial.py
pyscada/opcua/migrations/0002_add_device_protocol.py
pyscada/opcua/migrations/0003_auto_20211217_1024.py
pyscada/opcua/migrations/0004_opcuadevice_remote_devices_objects.py
pyscada/opcua/migrations/0005_auto_20211217_1046.py
pyscada/opcua/migrations/0006_auto_20211217_1406.py
pyscada/opcua/migrations/0007_auto_20211217_1617.py
pyscada/opcua/migrations/0008_auto_20220118_1046.py
pyscada/opcua/migrations/0009_auto_20220119_0904.py
pyscada/opcua/migrations/0010_devicehandler_migration.py
pyscada/opcua/migrations/0011_remove_opcuadevice_instrument_handler.py
pyscada/opcua/migrations/__init__.py
pyscada_opcua-0.8.0.dist-info/AUTHORS
pyscada_opcua-0.8.0.dist-info/LICENSE
pyscada_opcua-0.8.0.dist-info/METADATA
pyscada_opcua-0.8.0.dist-info/WHEEL
pyscada_opcua-0.8.0.dist-info/top_level.txt
pyscada_opcua-0.8.0.dist-info/RECORD
